a9x_webstatistics/__init__.py
a9x_webstatistics/gencockpit.py
a9x_webstatistics/gencockpitV0001.py
a9x_webstatistics/genqualityV0001.py
a9x_webstatistics/main.py
a9x_webstatistics/migratev0001.py
a9x_webstatistics/module1.py
a9x_webstatistics/parseRecJsonV0001.py
a9x_webstatistics/sumDayV0001.py
a9x_webstatistics/summarizemonth.py
a9x_webstatistics/summarizemonthV0001.py
a9x_webstatistics/updateStatisticsV0001.py
a9x_webstatistics/updatestatistics.py
a9x_webstatistics/cleanupV0001/__init__.py
a9x_webstatistics/cleanupV0001/cleanupQuality.py
a9x_webstatistics/gencockpitsubV0001/__init__.py
a9x_webstatistics/gencockpitsubV0001/cockpitlanguages.py
a9x_webstatistics/gencockpitsubV0001/dailyHits.py
a9x_webstatistics/gencockpitsubV0001/dailyquality.py
a9x_webstatistics/gencockpitsubV0001/dailytopcountries.py
a9x_webstatistics/gencockpitsubV0001/dailytopdomains.py
a9x_webstatistics/gencockpitsubV0001/dailytopurl.py
a9x_webstatistics/gencockpitsubV0001/externalfriends.py
a9x_webstatistics/gencockpitsubV0001/genheader.py
a9x_webstatistics/gencockpitsubV0001/makenodeslinks.py
a9x_webstatistics/gencockpitsubV0001/monthlyHits.py
a9x_webstatistics/gencockpitsubV0001/monthlytopcountries.py
a9x_webstatistics/gencockpitsubV0001/monthlytopdomains.py
a9x_webstatistics/gencockpitsubV0001/monthlytopurl.py
a9x_webstatistics/gencockpitsubV0001/navChord.py
a9x_webstatistics/gencockpitsubV0001/nav_chord_longterm.py
a9x_webstatistics/gencockpitsubV0001/navchart.py
a9x_webstatistics/gencockpitsubV0001/navchartsankey.py
a9x_webstatistics/gencockpitsubV0001/navtangledtree.py
a9x_webstatistics/gencockpitsubV0001/navtangledtree2.py
a9x_webstatistics/gencockpitsubV0001/performance.py
a9x_webstatistics/gencockpitsubV0001/validip.py
a9x_webstatistics/genqualitysubV0001/__init__.py
a9x_webstatistics/genqualitysubV0001/quality500.py
a9x_webstatistics/migV0001/__init__.py
a9x_webstatistics/migV0001/migrateV0001sub0001.py
a9x_webstatistics/sumV0001/__init__.py
a9x_webstatistics-1.8.17.dist-info/licenses/LICENSE
a9x_webstatistics-1.8.17.dist-info/METADATA
a9x_webstatistics-1.8.17.dist-info/WHEEL
a9x_webstatistics-1.8.17.dist-info/top_level.txt
a9x_webstatistics-1.8.17.dist-info/RECORD
