Metadata-Version: 2.4
Name: a9x_webstatistics
Version: 1.8.17
Summary: Web Statistics and Analytics Package
Home-page: https://github.com/ava007/a9x-webstatistics
Author: André von Arx
Author-email: avonarx@outlook.de
Project-URL: Documentation, https://github.com/ava007/a9x-webstatistics
Project-URL: Bug Reports, https://github.com/ava007/a9x-webstatistics/issues
Project-URL: Source Code, https://github.com/ava007/a9x-webstatistics
Keywords: webstats,statistics,analytics
Classifier: Development Status :: 5 - Production/Stable
Classifier: Intended Audience :: Developers
Classifier: Intended Audience :: Information Technology
Classifier: Topic :: Internet
Classifier: Topic :: Internet :: Log Analysis
Classifier: Programming Language :: Python :: 3
Classifier: Programming Language :: Python :: 3.9
Classifier: Programming Language :: Python :: 3.10
Classifier: Programming Language :: Python :: 3.11
Classifier: Programming Language :: Python :: 3.12
Classifier: Programming Language :: Python :: 3.13
Classifier: Programming Language :: Python :: 3 :: Only
Classifier: License :: OSI Approved :: MIT License
Classifier: Operating System :: OS Independent
Requires-Python: >=3.8
License-File: LICENSE
Requires-Dist: geoip2
Provides-Extra: dev
Requires-Dist: check-manifest; extra == "dev"
Dynamic: author
Dynamic: author-email
Dynamic: classifier
Dynamic: description
Dynamic: description-content-type
Dynamic: home-page
Dynamic: keywords
Dynamic: license-file
Dynamic: project-url
Dynamic: provides-extra
Dynamic: requires-dist
Dynamic: requires-python
Dynamic: summary
